Metadata-Version: 2.1
Name: discord-holo-api
Version: 1.3.0
Summary: Python module for API holo
Home-page: https://github.com/gimartmart/discord_holo_api_py
Author: mandarin
Author-email: burjtyuu@gmail.com
License: UNKNOWN
Platform: UNKNOWN
Classifier: Programming Language :: Python :: 3
Classifier: License :: OSI Approved :: MIT License
Classifier: Operating System :: OS Independent
Requires-Python: >= 3.6,
